lerobot_policy_rewact/__init__.py
lerobot_policy_rewact/configuration_rewact.py
lerobot_policy_rewact/modeling_rewact.py
lerobot_policy_rewact/processor_rewact.py
lerobot_policy_rewact/utils.py
lerobot_policy_rewact/vision/__init__.py
lerobot_policy_rewact/vision/base.py
lerobot_policy_rewact/vision/dinov3.py
lerobot_policy_rewact/vision/resnet.py
lerobot_policy_rewact/vision/vjepa2.py
lerobot_policy_rewact-0.1.1.dist-info/licenses/LICENSE
lerobot_policy_rewact-0.1.1.dist-info/METADATA
lerobot_policy_rewact-0.1.1.dist-info/WHEEL
lerobot_policy_rewact-0.1.1.dist-info/top_level.txt
lerobot_policy_rewact-0.1.1.dist-info/RECORD
