Metadata-Version: 2.4
Name: lerobot_policy_rewact
Version: 0.1.1
Summary: RewACT: Reward-Augmented Action Chunking with Transformers - LeRobot Policy Plugin
Author: Ville Kuosmanen
License: MIT License
Classifier: Development Status :: 3 - Alpha
Classifier: Intended Audience :: Science/Research
Classifier: License :: OSI Approved :: MIT License
Classifier: Programming Language :: Python :: 3
Classifier: Programming Language :: Python :: 3.10
Classifier: Programming Language :: Python :: 3.11
Classifier: Topic :: Scientific/Engineering :: Artificial Intelligence
Requires-Python: >=3.10
License-File: LICENSE
Requires-Dist: lerobot>=0.4
Requires-Dist: einops>=0.6.0
Requires-Dist: torch
Requires-Dist: torchvision
Dynamic: license-file
